{
  "plugins": {
    "Comment.nvim": {
      "rev": "e30b7f2",
      "src": "https://github.com/numToStr/Comment.nvim"
    },
    "blink.cmp": {
      "rev": "bae4bae",
      "src": "https://github.com/saghen/blink.cmp",
      "version": "'v1.6.0'"
    },
    "conform.nvim": {
      "rev": "fbcb4fa",
      "src": "https://github.com/stevearc/conform.nvim"
    },
    "diffview.nvim": {
      "rev": "4516612",
      "src": "https://github.com/sindrets/diffview.nvim"
    },
    "everforest": {
      "rev": "3fffb09",
      "src": "https://github.com/sainnhe/everforest"
    },
    "gruvbox.nvim": {
      "rev": "5e0a460",
      "src": "https://github.com/ellisonleao/gruvbox.nvim"
    },
    "lazydev.nvim": {
      "rev": "e28ce52",
      "src": "https://github.com/folke/lazydev.nvim"
    },
    "mason.nvim": {
      "rev": "ad7146a",
      "src": "http://github.com/mason-org/mason.nvim"
    },
    "mini.pick": {
      "rev": "96ee37d",
      "src": "https://github.com/echasnovski/mini.pick"
    },
    "nvim-early-retirement": {
      "rev": "9109589",
      "src": "https://github.com/chrisgrieser/nvim-early-retirement"
    },
    "nvim-lspconfig": {
      "rev": "ac98db2",
      "src": "https://github.com/neovim/nvim-lspconfig"
    },
    "nvim-tree.lua": {
      "rev": "e397756",
      "src": "https://github.com/nvim-tree/nvim-tree.lua"
    },
    "nvim-treesitter": {
      "rev": "42fc28ba",
      "src": "https://github.com/nvim-treesitter/nvim-treesitter"
    },
    "nvim-ts-context-commentstring": {
      "rev": "1b212c2",
      "src": "https://github.com/JoosepAlviste/nvim-ts-context-commentstring"
    },
    "nvim-web-devicons": {
      "rev": "b8221e4",
      "src": "https://github.com/nvim-tree/nvim-web-devicons"
    },
    "plenary.nvim": {
      "rev": "b9fd522",
      "src": "https://github.com/nvim-lua/plenary.nvim"
    },
    "sonokai": {
      "rev": "cf50520",
      "src": "https://github.com/sainnhe/sonokai"
    },
    "tokyonight.nvim": {
      "rev": "d14614c",
      "src": "https://github.com/folke/tokyonight.nvim"
    }
  }
}